scdataloader/__init__.py
scdataloader/__main__.py
scdataloader/base.py
scdataloader/collator.py
scdataloader/config.py
scdataloader/data.py
scdataloader/datamodule.py
scdataloader/mapped.py
scdataloader/preprocess.py
scdataloader/utils.py
scdataloader-2.0.11.dist-info/METADATA
scdataloader-2.0.11.dist-info/WHEEL
scdataloader-2.0.11.dist-info/entry_points.txt
scdataloader-2.0.11.dist-info/licenses/LICENSE
scdataloader-2.0.11.dist-info/RECORD
