Metadata-Version: 2.4
Name: scdataloader
Version: 2.0.11
Summary: a dataloader for single cell data in lamindb
Project-URL: repository, https://github.com/jkobject/scDataLoader
Author-email: jkobject <jkobject@gmail.com>
License-Expression: MIT
License-File: LICENSE
Keywords: dataloader,lamindb,pytorch,scPRINT,scRNAseq
Requires-Python: <3.13,>=3.10
Requires-Dist: anndata>=0.9.0
Requires-Dist: biomart>=0.9.0
Requires-Dist: cellxgene-census>=0.1.0
Requires-Dist: django>=4.0.0
Requires-Dist: ipykernel>=6.20.0
Requires-Dist: jupytext>=1.16.0
Requires-Dist: lamindb[bionty,jupyter,zarr]==1.6.2
Requires-Dist: leidenalg>=0.8.0
Requires-Dist: lightning>=2.3.0
Requires-Dist: matplotlib>=3.5.0
Requires-Dist: numpy<=2.2.0
Requires-Dist: pandas>=2.0.0
Requires-Dist: pytorch-lightning>=2.3.0
Requires-Dist: scikit-misc>=0.5.0
Requires-Dist: seaborn>=0.11.0
Requires-Dist: torch>=2.2.0
Requires-Dist: torchdata>=0.5.0
Requires-Dist: zarr>=2.10.0
Provides-Extra: dev
Requires-Dist: coverage>=7.3.2; extra == 'dev'
Requires-Dist: gitchangelog>=3.0.4; extra == 'dev'
Requires-Dist: mkdocs-git-authors-plugin>=0.4.0; extra == 'dev'
Requires-Dist: mkdocs-git-revision-date-localized-plugin>=1.0.0; extra == 'dev'
Requires-Dist: mkdocs-jupyter>=0.2.0; extra == 'dev'
Requires-Dist: mkdocs>=1.5.3; extra == 'dev'
Requires-Dist: mkdocstrings-python>=0.10.0; extra == 'dev'
Requires-Dist: mkdocstrings>=0.22.0; extra == 'dev'
Requires-Dist: pytest-cov>=4.1.0; extra == 'dev'
Requires-Dist: pytest>=7.4.3; extra == 'dev'
Requires-Dist: ruff>=0.6.4; extra == 'dev'
